Workbook

Sheet 01 Income Statement
A1: Pro Forma Income Statement (6-Quarter Cumulative)
A3: Income Statement ($M) | B3: P1 | C3: P2 | D3: P3 | E3: Total
A4: Revenue
A5: Direct Revenue | B5: 61 | C5: 0 | D5: 6.9 | E5: 67.9
A6: Halo Revenue | B6: 0 | C6: 0 | D6: 15 | E6: 15
A7: Total Revenue | B7: 61 | C7: 0 | D7: 21.9 | E7: 82.9
A9: Cost of Goods Sold (COGS) | B9: -23.6 | C9: 0 | D9: -8.4 | E9: -32
A10: Gross Profit | B10: 37.4 | C10: 0 | D10: 13.5 | E10: 50.9
A12: Operating Impact
A13: Cost Savings (P2) | B13: 0 | C13: 18 | D13: 0 | E13: 18
A15: Total Operating Benefit | B15: 37.4 | C15: 18 | D15: 13.5 | E15: 68.9
A17: Operating Expenses (platform, ops) | B17: -3 | C17: -2.5 | D17: -1.5 | E17: -7
A19: EBITDA (Program) | E19: 61.9
A21: Investment (CapEx) | B21: -15 | C21: -20 | D21: -10 | E21: -45
A22: Contingency | B22: 0 | C22: 0 | D22: 0 | E22: -5
A24: Net Profit (Program Level) | E24: 50

Sheet 02 Cash Flow
A1: Pro Forma Cash Flow Statement (Quarterly)
A4: Cash Flow ($M) | B4: Q1 | C4: Q2 | D4: Q3 | E4: Q4 | F4: Q5 | G4: Q6 | H4: Total
A5: Cash Inflows
A6: P1 Revenue | B6: 0 | C6: 1 | D6: 5 | E6: 12 | F6: 20 | G6: 23 | H6: 61
A7: P2 Savings | B7: 0 | C7: 0.5 | D7: 2 | E7: 4 | F7: 5.5 | G7: 6 | H7: 18
A8: P3 Revenue | B8: 0.4 | C8: 1.3 | D8: 1.3 | E8: 1.3 | F8: 1.3 | G8: 1.3 | H8: 6.9
A9: P3 Halo | B9: 0.5 | C9: 2 | D9: 3 | E9: 3 | F9: 3.5 | G9: 3 | H9: 15
A10: Total Inflows | B10: 0.9 | C10: 4.8 | D10: 11.3 | E10: 20.3 | F10: 30.3 | G10: 33.3 | H10: 100.9
A12: Cash Outflows
A13: Proposals
A14: CapEx
A15: P1 — Recommendation Engine | B15: ='CapEx & OpEx Calculations'!B3 -> 3 | C15: ='CapEx & OpEx Calculations'!C3 -> 3 | D15: ='CapEx & OpEx Calculations'!D3 -> 2.5 | E15: ='CapEx & OpEx Calculations'!E3 -> 2.5 | F15: ='CapEx & OpEx Calculations'!F3 -> 2 | G15: ='CapEx & OpEx Calculations'!G3 -> 2 | H15: =SUM(B15:G15) -> 15
A16: P2 — AI Design | B16: ='CapEx & OpEx Calculations'!B7 -> 4 | C16: ='CapEx & OpEx Calculations'!C7 -> 4 | D16: ='CapEx & OpEx Calculations'!D7 -> 3.5 | E16: ='CapEx & OpEx Calculations'!E7 -> 3.5 | F16: ='CapEx & OpEx Calculations'!F7 -> 2.5 | G16: ='CapEx & OpEx Calculations'!G7 -> 2.5 | H16: =SUM(B16:G16) -> 20
A17: P3 — Capsule Fund | B17: ='CapEx & OpEx Calculations'!B11 -> 1.5 | C17: ='CapEx & OpEx Calculations'!C11 -> 1.5 | D17: ='CapEx & OpEx Calculations'!D11 -> 1.5 | E17: ='CapEx & OpEx Calculations'!E11 -> 1.5 | F17: ='CapEx & OpEx Calculations'!F11 -> 2 | G17: ='CapEx & OpEx Calculations'!G11 -> 2 | H17: =SUM(B17:G17) -> 10
A18: Contingency Reserve (unallocated) | B18: ='CapEx & OpEx Calculations'!B15 -> 0 | C18: ='CapEx & OpEx Calculations'!C15 -> 0.5 | D18: ='CapEx & OpEx Calculations'!D15 -> 1 | E18: ='CapEx & OpEx Calculations'!E15 -> 1.5 | F18: ='CapEx & OpEx Calculations'!F15 -> 1 | G18: ='CapEx & OpEx Calculations'!G15 -> 1 | H18: =SUM(B18:G18) -> 5
A19: Total CapEx | B19: =SUM(B15:B18) -> 8.5 | C19: =SUM(C15:C18) -> 9 | D19: =SUM(D15:D18) -> 8.5 | E19: =SUM(E15:E18) -> 9 | F19: =SUM(F15:F18) -> 7.5 | G19: =SUM(G15:G18) -> 7.5 | H19: =SUM(H15:H18) -> 50
A21: OpEx
A22: P1 — Recommendation Engine | B22: ='CapEx & OpEx Calculations'!B22 -> 0.3 | C22: ='CapEx & OpEx Calculations'!C22 -> 0.5 | D22: ='CapEx & OpEx Calculations'!D22 -> 0.7 | E22: ='CapEx & OpEx Calculations'!E22 -> 0.8 | F22: ='CapEx & OpEx Calculations'!F22 -> 0.9 | G22: ='CapEx & OpEx Calculations'!G22 -> 0.8 | H22: =SUM(B22:G22) -> 4
A23: P2 — AI Design | B23: ='CapEx & OpEx Calculations'!B25 -> 0.2 | C23: ='CapEx & OpEx Calculations'!C25 -> 0.3 | D23: ='CapEx & OpEx Calculations'!D25 -> 0.5 | E23: ='CapEx & OpEx Calculations'!E25 -> 0.6 | F23: ='CapEx & OpEx Calculations'!F25 -> 0.7 | G23: ='CapEx & OpEx Calculations'!G25 -> 0.7 | H23: =SUM(B23:G23) -> 3
A24: P3 — Capsule Fund | B24: ='CapEx & OpEx Calculations'!B28 -> 0.6 | C24: ='CapEx & OpEx Calculations'!C28 -> 1.1 | D24: ='CapEx & OpEx Calculations'!D28 -> 1.3 | E24: ='CapEx & OpEx Calculations'!E28 -> 1.5 | F24: ='CapEx & OpEx Calculations'!F28 -> 1.7 | G24: ='CapEx & OpEx Calculations'!G28 -> 1.7 | H24: =SUM(B24:G24) -> 7.9
A25: Total OpEx | B25: =SUM(B22:B24) -> 1.1 | C25: =SUM(C22:C24) -> 1.9 | D25: =SUM(D22:D24) -> 2.5 | E25: =SUM(E22:E24) -> 2.9 | F25: =SUM(F22:F24) -> 3.3 | G25: =SUM(G22:G24) -> 3.2 | H25: =SUM(H22:H24) -> 14.9
A27: Program Spend | B27: =B19+B25 -> 9.6 | C27: =C19+C25 -> 10.9 | D27: =D19+D25 -> 11 | E27: =E19+E25 -> 11.9 | F27: =F19+F25 -> 10.8 | G27: =G19+G25 -> 10.7 | H27: =H19+H25 -> 64.9
A29: Net Cash Flow | B29: =B10-B27 -> -8.7 | C29: =C10-C27 -> -6.1 | D29: =D10-D27 -> 0.3 | E29: =E10-E27 -> 8.4 | F29: =F10-F27 -> 19.5 | G29: =G10-G27 -> 22.6 | H29: =H10-H27 -> 36
A31: Cumulative Cash Flow | B31: =B29 -> -8.7 | C31: =B31+C29 -> -14.8 | D31: =C31+D29 -> -14.5 | E31: =D31+E29 -> -6.1 | F31: =E31+F29 -> 13.4 | G31: =F31+G29 -> 36

Sheet CapEx & OpEx Calculations
A2: CapEx ($M) | B2: Q1 | C2: Q2 | D2: Q3 | E2: Q4 | F2: Q5 | G2: Q6 | H2: Total
A3: P1 – Recommendation Engine | B3: =SUM(B4:B5) -> 3 | C3: =SUM(C4:C5) -> 3 | D3: =SUM(D4:D5) -> 2.5 | E3: =SUM(E4:E5) -> 2.5 | F3: =SUM(F4:F5) -> 2 | G3: =SUM(G4:G5) -> 2 | H3: =SUM(H4:H5) -> 15
A4: Core Build & Integration | B4: 2.5 | C4: 2.5 | D4: 2 | E4: 2 | F4: 1.5 | G4: 1.5 | H4: 12
A5: Social Trend Layer | B5: 0.5 | C5: 0.5 | D5: 0.5 | E5: 0.5 | F5: 0.5 | G5: 0.5 | H5: 3
A7: P2 – AI Design | B7: =SUM(B8:B9) -> 4 | C7: =SUM(C8:C9) -> 4 | D7: =SUM(D8:D9) -> 3.5 | E7: =SUM(E8:E9) -> 3.5 | F7: =SUM(F8:F9) -> 2.5 | G7: =SUM(G8:G9) -> 2.5 | H7: =SUM(H8:H9) -> 20
A8: 3D Sampling & Tool Setup (CapEx) | B8: 2.5 | C8: 2.5 | D8: 2 | E8: 2 | F8: 1.5 | G8: 1.5 | H8: 12
A9: Intelligence Layer & Validation (CapEx) | B9: 1.5 | C9: 1.5 | D9: 1.5 | E9: 1.5 | F9: 1 | G9: 1 | H9: 8
A11: P3 – Capsule (Setup) | B11: =SUM(B12:B13) -> 1.5 | C11: =SUM(C12:C13) -> 1.5 | D11: =SUM(D12:D13) -> 1.5 | E11: =SUM(E12:E13) -> 1.5 | F11: =SUM(F12:F13) -> 2 | G11: =SUM(G12:G13) -> 2 | H11: =SUM(H12:H13) -> 10
A12: Licensing + Base Inventory (CapEx) | B12: 1.2 | C12: 1.2 | D12: 1.2 | E12: 1.2 | F12: 1.5 | G12: 1.5 | H12: 7.8
A13: Manufacturing Setup (CapEx) | B13: 0.3 | C13: 0.3 | D13: 0.3 | E13: 0.3 | F13: 0.5 | G13: 0.5 | H13: 2.2
A15: Contingency | B15: 0 | C15: 0.5 | D15: 1 | E15: 1.5 | F15: 1 | G15: 1 | H15: 5
A18: Total CapEx | B18: =B3+B7+B11+B15 -> 8.5 | C18: =C3+C7+C11+C15 -> 9 | D18: =D3+D7+D11+D15 -> 8.5 | E18: =E3+E7+E11+E15 -> 9 | F18: =F3+F7+F11+F15 -> 7.5 | G18: =G3+G7+G11+G15 -> 7.5 | H18: 50
A21: OpEx ($M) | B21: Q1 | C21: Q2 | D21: Q3 | E21: Q4 | F21: Q5 | G21: Q6 | H21: Total
A22: P1 – Recommendation Engine | B22: =SUM(B23:B23) -> 0.3 | C22: =SUM(C23:C23) -> 0.5 | D22: =SUM(D23:D23) -> 0.7 | E22: =SUM(E23:E23) -> 0.8 | F22: =SUM(F23:F23) -> 0.9 | G22: =SUM(G23:G23) -> 0.8 | H22: =SUM(H23:H23) -> 4
A23: Platform Ops & Maintenance (OpEx) | B23: 0.3 | C23: 0.5 | D23: 0.7 | E23: 0.8 | F23: 0.9 | G23: 0.8 | H23: 4
A25: P2 – AI Design | B25: =SUM(B26:B26) -> 0.2 | C25: =SUM(C26:C26) -> 0.3 | D25: =SUM(D26:D26) -> 0.5 | E25: =SUM(E26:E26) -> 0.6 | F25: =SUM(F26:F26) -> 0.7 | G25: =SUM(G26:G26) -> 0.7 | H25: =SUM(H26:H26) -> 3
A26: Tools, Talent & Governance (OpEx) | B26: 0.2 | C26: 0.3 | D26: 0.5 | E26: 0.6 | F26: 0.7 | G26: 0.7 | H26: 3
A28: P3 – Capsule (Setup) | B28: =SUM(B29:B30) -> 0.6 | C28: =SUM(C29:C30) -> 1.1 | D28: =SUM(D29:D30) -> 1.3 | E28: =SUM(E29:E30) -> 1.5 | F28: =SUM(F29:F30) -> 1.7 | G28: =SUM(G29:G30) -> 1.7 | H28: =SUM(H29:H30) -> 7.9
A29: Marketing & Activation (OpEx) | B29: 0.4 | C29: 0.7 | D29: 0.8 | E29: 0.9 | F29: 1 | G29: 1 | H29: 4.8
A30: Decoration & Fulfillment (OpEx) | B30: 0.2 | C30: 0.4 | D30: 0.5 | E30: 0.6 | F30: 0.7 | G30: 0.7 | H30: 3.1
A32: Total OpEx | B32: =B22+B25+B28 -> 1.1 | C32: =C22+C25+C28 -> 1.9 | D32: =D22+D25+D28 -> 2.5 | E32: =E22+E25+E28 -> 2.9 | F32: =F22+F25+F28 -> 3.3 | G32: =G22+G25+G28 -> 3.2 | H32: =H22+H25+H28 -> 14.9
